xSlack-0.2.dist-info/DESCRIPTION.rst
xSlack-0.2.dist-info/METADATA
xSlack-0.2.dist-info/RECORD
xSlack-0.2.dist-info/WHEEL
xSlack-0.2.dist-info/entry_points.txt
xSlack-0.2.dist-info/metadata.json
xSlack-0.2.dist-info/top_level.txt
xslack/__init__.py
xslack/xslack.py
