Metadata-Version: 2.0
Name: xSlack
Version: 0.2
Summary: Open source, self hosted cross-team channels for Slack!
Home-page: https://xslack.io/
Author: Henrik Lilleengen
Author-email: xslack@ithenrik.com
License: MIT
Keywords: slack cross-team cross team share chat channel xslack
Platform: UNKNOWN
Classifier: Development Status :: 3 - Alpha
Classifier: Intended Audience :: System Administrators
Classifier: Topic :: Communications :: Chat
Classifier: License :: OSI Approved :: MIT License
Classifier: Programming Language :: Python :: 3
Classifier: Programming Language :: Python :: 3.3
Classifier: Programming Language :: Python :: 3.4
Classifier: Programming Language :: Python :: 3.5
Requires-Dist: requests
Requires-Dist: slackclient
